XStatic_Select2-4.0.13.2-nspkg.pth
xstatic/pkg/select2/__init__.py
xstatic/pkg/select2/data/select2.css
xstatic/pkg/select2/data/select2.full.js
xstatic/pkg/select2/data/select2.full.min.js
xstatic/pkg/select2/data/select2.js
xstatic/pkg/select2/data/select2.min.css
xstatic/pkg/select2/data/select2.min.js
xstatic/pkg/select2/data/i18n/af.js
xstatic/pkg/select2/data/i18n/ar.js
xstatic/pkg/select2/data/i18n/az.js
xstatic/pkg/select2/data/i18n/bg.js
xstatic/pkg/select2/data/i18n/bn.js
xstatic/pkg/select2/data/i18n/bs.js
xstatic/pkg/select2/data/i18n/ca.js
xstatic/pkg/select2/data/i18n/cs.js
xstatic/pkg/select2/data/i18n/da.js
xstatic/pkg/select2/data/i18n/de.js
xstatic/pkg/select2/data/i18n/dsb.js
xstatic/pkg/select2/data/i18n/el.js
xstatic/pkg/select2/data/i18n/en.js
xstatic/pkg/select2/data/i18n/es.js
xstatic/pkg/select2/data/i18n/et.js
xstatic/pkg/select2/data/i18n/eu.js
xstatic/pkg/select2/data/i18n/fa.js
xstatic/pkg/select2/data/i18n/fi.js
xstatic/pkg/select2/data/i18n/fr.js
xstatic/pkg/select2/data/i18n/gl.js
xstatic/pkg/select2/data/i18n/he.js
xstatic/pkg/select2/data/i18n/hi.js
xstatic/pkg/select2/data/i18n/hr.js
xstatic/pkg/select2/data/i18n/hsb.js
xstatic/pkg/select2/data/i18n/hu.js
xstatic/pkg/select2/data/i18n/hy.js
xstatic/pkg/select2/data/i18n/id.js
xstatic/pkg/select2/data/i18n/is.js
xstatic/pkg/select2/data/i18n/it.js
xstatic/pkg/select2/data/i18n/ja.js
xstatic/pkg/select2/data/i18n/ka.js
xstatic/pkg/select2/data/i18n/km.js
xstatic/pkg/select2/data/i18n/ko.js
xstatic/pkg/select2/data/i18n/lt.js
xstatic/pkg/select2/data/i18n/lv.js
xstatic/pkg/select2/data/i18n/mk.js
xstatic/pkg/select2/data/i18n/ms.js
xstatic/pkg/select2/data/i18n/nb.js
xstatic/pkg/select2/data/i18n/ne.js
xstatic/pkg/select2/data/i18n/nl.js
xstatic/pkg/select2/data/i18n/pl.js
xstatic/pkg/select2/data/i18n/ps.js
xstatic/pkg/select2/data/i18n/pt-BR.js
xstatic/pkg/select2/data/i18n/pt.js
xstatic/pkg/select2/data/i18n/ro.js
xstatic/pkg/select2/data/i18n/ru.js
XStatic_Select2-4.0.13.2.dist-info/METADATA
XStatic_Select2-4.0.13.2.dist-info/WHEEL
XStatic_Select2-4.0.13.2.dist-info/namespace_packages.txt
XStatic_Select2-4.0.13.2.dist-info/top_level.txt
XStatic_Select2-4.0.13.2.dist-info/RECORD
