Metadata-Version: 2.1
Name: XStatic-Select2
Version: 4.0.13.2
Summary: Select2 4.0.13 (XStatic packaging standard)
Home-page: http://select2.github.io/
Maintainer: Benjamin Dauvergne
Maintainer-email: bdauvergne@entrouvert.com
License: (same as Select2)
Keywords: select2 xstatic
Platform: any
